clumpsptm/__init__.py
clumpsptm/__main__.py
clumpsptm/pdbstore.py
clumpsptm/utils.py
clumpsptm/clumps/__init__.py
clumpsptm/clumps/engine.py
clumpsptm/clumps/funcs.py
clumpsptm/mapping/__init__.py
clumpsptm/mapping/blast.py
clumpsptm/mapping/ref.py
clumpsptm/samplers/__init__.py
clumpsptm/samplers/ptm.py
clumpsptm/vis/__init__.py
clumpsptm/vis/mol.py
clumpsptm/vis/plotting.py
clumps_ptm-0.0.6.dist-info/LICENSE
clumps_ptm-0.0.6.dist-info/METADATA
clumps_ptm-0.0.6.dist-info/WHEEL
clumps_ptm-0.0.6.dist-info/entry_points.txt
clumps_ptm-0.0.6.dist-info/top_level.txt
clumps_ptm-0.0.6.dist-info/RECORD
