Metadata-Version: 2.1
Name: clumps-ptm
Version: 0.0.6
Summary: CLUMPS-PTM driver gene discovery using 3D protein structure (Getz Lab).
Home-page: https://github.com/getzlab/CLUMPS-PTM
Author: Shankara Anand
Author-email: sanand@broadinstitute.org
License: UNKNOWN
Keywords: cancer,bioinformatics,genomics,proteomics,proteins,alphafold,post-translational modifications,phosphorylation,acetylation
Platform: UNKNOWN
Classifier: Development Status :: 3 - Alpha
Classifier: Programming Language :: Python :: 3
Classifier: Intended Audience :: Science/Research
Classifier: Topic :: Scientific/Engineering :: Bio-Informatics
Classifier: Typing :: Typed
Classifier: License :: OSI Approved :: MIT License
Requires-Python: >=3.6
Requires-Dist: matplotlib (>=3.2.1)
Requires-Dist: twobitreader (>=3.1.7)
Requires-Dist: statsmodels (>=0.9.0)
Requires-Dist: scipy (>=1.3.0)
Requires-Dist: pyopenssl (>=19.0.0)
Requires-Dist: prody (>=1.10.10)
Requires-Dist: lxml (>=4.3.4)
Requires-Dist: biopython (>=1.73)
Requires-Dist: tqdm (>=4.32.1)
Requires-Dist: agutil
